data_platform_catalogue/__init__.py
data_platform_catalogue/client/__init__.py
data_platform_catalogue/client/datahub_client.py
data_platform_catalogue/client/exceptions.py
data_platform_catalogue/client/graphql/__init__.py
data_platform_catalogue/client/graphql/facets.graphql
data_platform_catalogue/client/graphql/getChartDetails.graphql
data_platform_catalogue/client/graphql/getDatasetDetails.graphql
data_platform_catalogue/client/graphql/getGlossaryTerms.graphql
data_platform_catalogue/client/graphql/listContainerEntities.graphql
data_platform_catalogue/client/graphql/search.graphql
data_platform_catalogue/client/graphql_helpers.py
data_platform_catalogue/client/search.py
data_platform_catalogue/entities.py
data_platform_catalogue/search_types.py
ministryofjustice_data_platform_catalogue-1.0.1.dist-info/METADATA
ministryofjustice_data_platform_catalogue-1.0.1.dist-info/WHEEL
ministryofjustice_data_platform_catalogue-1.0.1.dist-info/RECORD
