Metadata-Version: 2.1
Name: ministryofjustice-data-platform-catalogue
Version: 1.0.1
Summary: Wrapper around Datahub supporting custom properties for the Find MOJ Data service.
License: MIT
Author: MoJ Data Platform Team
Author-email: data-platform-tech@digital.justice.gov.uk
Requires-Python: >=3.10,<4.0
Classifier: License :: OSI Approved :: MIT License
Classifier: Programming Language :: Python :: 3
Classifier: Programming Language :: Python :: 3.10
Classifier: Programming Language :: Python :: 3.11
Classifier: Programming Language :: Python :: 3.12
Requires-Dist: acryl-datahub[datahub-rest] (>=0.12.1.3,<0.13.0.0)
Requires-Dist: deepdiff (>=6.7.1,<7.0.0)
Requires-Dist: freezegun (>=1.4.0,<2.0.0)
Requires-Dist: pydantic (>=2.7.1,<3.0.0)
